pypi_mcp_test/__init__.py
pypi_mcp_test/__main__.py
pypi_mcp_test/pypi_mcp_test.py
pypi_mcp_test-0.1.2.dist-info/METADATA
pypi_mcp_test-0.1.2.dist-info/WHEEL
pypi_mcp_test-0.1.2.dist-info/entry_points.txt
pypi_mcp_test-0.1.2.dist-info/RECORD
