Metadata-Version: 2.4
Name: pypi-mcp-test
Version: 0.1.2
Summary: A test mcp service to add numbers
Author-email: “RonanMcGovern” <78278410+RonanKMcGovern@users.noreply.github.com>
Requires-Python: >=3.12
Requires-Dist: build>=1.2.2.post1
Requires-Dist: mcp[cli]>=1.6.0
Requires-Dist: twine>=6.1.0
